setup.cfg
setup.py
asciigraphic/__init__.py
asciigraphic/__main__.py
asciigraphic.egg-info/PKG-INFO
asciigraphic.egg-info/SOURCES.txt
asciigraphic.egg-info/dependency_links.txt
asciigraphic.egg-info/entry_points.txt
asciigraphic.egg-info/not-zip-safe
asciigraphic.egg-info/requires.txt
asciigraphic.egg-info/top_level.txt