Metadata-Version: 1.0
Name: asciigraphic
Version: 0.1.dev0
Summary: Ascii graphic
Home-page: https://gitthub.com/chetnuy/ascii
Author: chetnuy
Author-email: chetnuy@gmail.com
License: GPU
Keywords: ascii graph console
Platform: UNKNOWN
